bcch/__init__.py
bcch/bcch.py
bcch/macro_series/__init__.py
bcch/macro_series/macro_series_api.py
bcch/request_handler_class/__init__.py
bcch/request_handler_class/request_handler.py
bcch-0.0.2.dist-info/LICENSE
bcch-0.0.2.dist-info/METADATA
bcch-0.0.2.dist-info/WHEEL
bcch-0.0.2.dist-info/top_level.txt
bcch-0.0.2.dist-info/RECORD
