Metadata-Version: 2.1
Name: bcch
Version: 0.0.2
Summary: Cliente en Python para la API del Banco Central de Chile
Home-page: https://github.com/LautaroParada/bcch-sdk
Author: Lautaro Parada Opazo
Author-email: lautaro.parada.opazo@gmail.com
License: Apache License 2.0
Platform: UNKNOWN
License-File: LICENSE
Requires-Dist: requests
